counter4bit/counter4bit.v
module counter4bit(clk,rst,q);
input clk,rst;
output reg [3:0]q;

always@(posedge clk)
begin
if(rst)
q<=0;
else
q<=q+1'b1;

end

endmodule

counter4bit/tb_counter4bit.v
`timescale 1ns/1ps
module tb_counter4bit;

reg clk,rst;
wire [3:0]q;

counter4bit dut(clk,rst,q);

initial

begin
$monitor("@time %gns clk=%b rst=%b q=%0d", $time, clk,rst,q);
clk=0;
rst=0;
#5 rst=1;
#5 rst=0;
end

always
#5 clk=~clk;

initial
#200 $stop;

initial
begin
$dumpfile("counter4bit.vcd");
$dumpvars(1);
end

endmodule

counter4bit/counter4bit.vcd
$date
	Wed Aug 28 15:03:28 2024
$end
$version
	Icarus Verilog
$end
$timescale
	1ps
$end
$scope module tb_counter4bit $end
$var wire 4 ! q [3:0] $end
$var reg 1 " clk $end
$var reg 1 # rst $end
$upscope $end
$enddefinitions $end
$comment Show the parameter values. $end
$dumpall
$end
#0
$dumpvars
0#
0"
bx !
$end
#5000
b0 !
1"
1#
#10000
0"
0#
#15000
b1 !
1"
#20000
0"
#25000
b10 !
1"
#30000
0"
#35000
b11 !
1"
#40000
0"
#45000
b100 !
1"
#50000
0"
#55000
b101 !
1"
#60000
0"
#65000
b110 !
1"
#70000
0"
#75000
b111 !
1"
#80000
0"
#85000
b1000 !
1"
#90000
0"
#95000
b1001 !
1"
#100000
0"
#105000
b1010 !
1"
#110000
0"
#115000
b1011 !
1"
#120000
0"
#125000
b1100 !
1"
#130000
0"
#135000
b1101 !
1"
#140000
0"
#145000
b1110 !
1"
#150000
0"
#155000
b1111 !
1"
#160000
0"
#165000
b0 !
1"
#170000
0"
#175000
b1 !
1"
#180000
0"
#185000
b10 !
1"
#190000
0"
#195000
b11 !
1"
